django_include_apps/__init__.py
django_include_apps/main.py
django_include_apps/package_mappings.json
django_include_apps-1.0.0.dist-info/METADATA
django_include_apps-1.0.0.dist-info/WHEEL
django_include_apps-1.0.0.dist-info/entry_points.txt
django_include_apps-1.0.0.dist-info/top_level.txt
django_include_apps-1.0.0.dist-info/RECORD
