Metadata-Version: 2.4
Name: django-include-apps
Version: 1.0.0
Summary: Intelligent CLI tool to manage Django INSTALLED_APPS with smart package mapping and requirements.txt management
Author-email: ROHAN <rohanroni2019@gmail.com>
Maintainer-email: ROHAN <rohanroni2019@gmail.com>
License: MIT
Project-URL: Homepage, https://github.com/Rohan7654/django-include-apps
Project-URL: Documentation, https://github.com/Rohan7654/django-include-apps#readme
Project-URL: Repository, https://github.com/Rohan7654/django-include-apps
Project-URL: Bug Reports, https://github.com/Rohan7654/django-include-apps/issues
Project-URL: Changelog, https://github.com/Rohan7654/django-include-apps/blob/main/CHANGELOG.md
Keywords: django,django-apps,installed-apps,package-management,cli,requirements,django-packages,automation,development-tools
Classifier: Development Status :: 5 - Production/Stable
Classifier: Intended Audience :: Developers
Classifier: License :: OSI Approved :: MIT License
Classifier: Operating System :: OS Independent
Classifier: Operating System :: Microsoft :: Windows
Classifier: Operating System :: POSIX :: Linux
Classifier: Operating System :: MacOS
Classifier: Programming Language :: Python
Classifier: Programming Language :: Python :: 3
Classifier: Programming Language :: Python :: 3.8
Classifier: Programming Language :: Python :: 3.9
Classifier: Programming Language :: Python :: 3.10
Classifier: Programming Language :: Python :: 3.11
Classifier: Programming Language :: Python :: 3.12
Classifier: Programming Language :: Python :: 3 :: Only
Classifier: Framework :: Django
Classifier: Framework :: Django :: 2.2
Classifier: Framework :: Django :: 3.0
Classifier: Framework :: Django :: 3.1
Classifier: Framework :: Django :: 3.2
Classifier: Framework :: Django :: 4.0
Classifier: Framework :: Django :: 4.1
Classifier: Framework :: Django :: 4.2
Classifier: Framework :: Django :: 5.0
Classifier: Topic :: Software Development
Classifier: Topic :: Software Development :: Libraries :: Python Modules
Classifier: Topic :: Software Development :: Build Tools
Classifier: Topic :: Utilities
Classifier: Environment :: Console
Classifier: Natural Language :: English
Requires-Python: >=3.8
Requires-Dist: typer>=0.9.0
Requires-Dist: requests>=2.25.0
Requires-Dist: inquirer>=3.0.0
